wwd/__init__.py
wwd/_modidx.py
wwd/data.py
wwd/template.py
wwd-0.0.1.dist-info/LICENSE
wwd-0.0.1.dist-info/METADATA
wwd-0.0.1.dist-info/WHEEL
wwd-0.0.1.dist-info/entry_points.txt
wwd-0.0.1.dist-info/top_level.txt
wwd-0.0.1.dist-info/RECORD
