Metadata-Version: 2.1
Name: wwd
Version: 0.0.1
Home-page: https://github.com/mvkvc/wwd
Author: Marko Vukovic
Author-email: mail@mvk.vc
License: MIT License
Keywords: nbdev jupyter notebook python
Classifier: Development Status :: 4 - Beta
Classifier: Intended Audience :: Developers
Classifier: Natural Language :: English
Classifier: Programming Language :: Python :: 3.10
Classifier: License :: OSI Approved :: MIT License
Requires-Python: >=3.10
License-File: LICENSE
Provides-Extra: dev
